tremetrics/__init__.py
tremetrics/metrics.py
tremetrics-0.2.0.dist-info/LICENSE.txt
tremetrics-0.2.0.dist-info/METADATA
tremetrics-0.2.0.dist-info/WHEEL
tremetrics-0.2.0.dist-info/top_level.txt
tremetrics-0.2.0.dist-info/RECORD
