Metadata-Version: 2.1
Name: tremetrics
Version: 0.2.0
Summary: Tremendous Metrics
Home-page: https://gitlab.com/BCLegon/tremetrics
Author: B.C. Legon
Author-email: pypi@legon.it
License: MIT
License-File: LICENSE.txt
Requires-Dist: numpy
Requires-Dist: pytest
Requires-Dist: scikit-learn
